setup.py
tvimport.py
tvimport.egg-info/PKG-INFO
tvimport.egg-info/SOURCES.txt
tvimport.egg-info/dependency_links.txt
tvimport.egg-info/entry_points.txt
tvimport.egg-info/requires.txt
tvimport.egg-info/top_level.txt