Metadata-Version: 1.0
Name: tvimport
Version: 0.1.4.1
Summary: Daemon to automatically organize tv series
Home-page: https://github.com/LucaGas/tvimport
Author: Luca Gasperini
Author-email: luca.gasperini@gmail.com
License: UNKNOWN
Platform: UNKNOWN
